NPDD/__init__.py
NPDD/data.py
NPDD/models.py
NPDD/training_n_inference.py
NPDD/data_files/ki_training_w_pocket.pkl
NPDD/weights/NPASS_pocket_mse_gat_best_1.pt
npdd-0.0.11.dist-info/licenses/LICENSE
npdd-0.0.11.dist-info/METADATA
npdd-0.0.11.dist-info/WHEEL
npdd-0.0.11.dist-info/entry_points.txt
npdd-0.0.11.dist-info/top_level.txt
npdd-0.0.11.dist-info/RECORD
