Metadata-Version: 2.4
Name: NPDD
Version: 0.0.11
Summary: Natural Product - Protein Binding Affinity Prediction Toolkit
Author: Thao Nguyen et al.
License: MIT License
Requires-Python: >=3.8
License-File: LICENSE
Requires-Dist: torch==2.7.1
Requires-Dist: torch-geometric==2.6.1
Requires-Dist: numpy==1.26.4
Requires-Dist: tqdm==4.67.1
Requires-Dist: scikit-learn==1.7.0
Requires-Dist: scipy==1.12.0
Dynamic: license-file
